setup.py
pysett/__init__.py
pysett/settings.py
pysett.egg-info/PKG-INFO
pysett.egg-info/SOURCES.txt
pysett.egg-info/dependency_links.txt
pysett.egg-info/not-zip-safe
pysett.egg-info/requires.txt
pysett.egg-info/top_level.txt