Metadata-Version: 1.2
Name: pysett
Version: 0.6
Summary: Simple YAML settings
Home-page: https://github.com/mlackman/pysettings
Author: Mika Lackman
Author-email: mika.lackman@gmail.com
License: MIT
Platform: UNKNOWN
Requires-Python: >3.6
